my_chrome_bookmarks/__init__.py
my_chrome_bookmarks/bookmarks.py
my_chrome_bookmarks/bookmarks_test.py
my_chrome_bookmarks-1.2.0.dist-info/licenses/LICENSE
my_chrome_bookmarks-1.2.0.dist-info/WHEEL
my_chrome_bookmarks-1.2.0.dist-info/METADATA
my_chrome_bookmarks-1.2.0.dist-info/RECORD
