Metadata-Version: 2.4
Name: my_chrome_bookmarks
Version: 1.2.0
Summary: Utils to load local chrome bookmarks.
Keywords: google,chrome,bookmarks
Author-email: Conchylicultor <etiennefg.pot@gmail.com>
Requires-Python: >=3.8
Classifier: Programming Language :: Python :: 3
Classifier: Programming Language :: Python :: 3 :: Only
Classifier: License :: OSI Approved :: Apache Software License
Classifier: Intended Audience :: Developers
Classifier: Topic :: Software Development :: Libraries :: Python Modules
License-File: LICENSE
Requires-Dist: etils[epy]
Requires-Dist: pytest ; extra == "dev"
Requires-Dist: pytest-xdist ; extra == "dev"
Requires-Dist: black ; extra == "dev"
Project-URL: homepage, https://github.com/conchylicultor/my-chrome-bookmarks
Project-URL: repository, https://github.com/conchylicultor/my-chrome-bookmarks
Provides-Extra: dev
